[
    {
        "id": "0884afa2-5bb5-46a6-a4f0-9a2f817f6322",
        "name": "Hassan",
        "title": "Need Plumber",
        "description": "my home pipline was damage",
        "location": "Baldia Town",
        "phone_number": null,
        "status": "pending",
        "comments": [
            {
                "id": "7f962f1b-6b16-448a-be04-fe2dc908820e",
                "author": "Anonymous",
                "message": "i will help you",
                "text": "i will help you"
            }
        ]
    }
]